LICENSE
README.md
setup.cfg
setup.py
penlm/__init__.py
penlm/adaptive_lasso.py
penlm/anisotropic_ridge_estimator.py
penlm/bar_estimator.py
penlm/base_estimators.py
penlm/grid_search.py
penlm/non_negative_garrote.py
penlm/relaxed_lasso.py
penlm/ridge_estimator.py
penlm/smooth_linear_model.py
penlm/smoothly_adaptively_centered_ridge.py
penlm.egg-info/PKG-INFO
penlm.egg-info/SOURCES.txt
penlm.egg-info/dependency_links.txt
penlm.egg-info/requires.txt
penlm.egg-info/top_level.txt