Metadata-Version: 2.1
Name: penlm
Version: 1.1.0
Summary: Penalized Linear Models for Classification and Regression
Home-page: https://github.com/bellibot/penlm
Author: Edoardo Belli
Author-email: iedobelli@gmail.com
License: MIT
Download-URL: https://github.com/bellibot/penlm/archive/refs/tags/v1.1.0.tar.gz
Keywords: Classification,Regression,Linear,Penalty
Platform: UNKNOWN
Classifier: Development Status :: 5 - Production/Stable
Requires-Python: >=3.5
License-File: LICENSE
